ShitDB/__init__.py
ShitDB/_async.py
ShitDB/core.py
ShitDB/errors.py
ShitDB/utils.py
ShitDB-1.1.dist-info/LICENSE.txt
ShitDB-1.1.dist-info/METADATA
ShitDB-1.1.dist-info/WHEEL
ShitDB-1.1.dist-info/top_level.txt
ShitDB-1.1.dist-info/RECORD
