Metadata-Version: 2.1
Name: ShitDB
Version: 1.1
Summary: A json database to fix the persistence problem on Heroku using Github!!
Home-page: UNKNOWN
Author: v1s1t0r999
License: UNKNOWN
Platform: UNKNOWN
Classifier: Programming Language :: Python :: 3
Classifier: License :: OSI Approved :: MIT License
Classifier: Operating System :: OS Independent
Requires-Python: >=3.6
